navidad/__init__.py
navidad/main.py
navidad-1.0.0.dist-info/licenses/LICENSE
navidad-1.0.0.dist-info/METADATA
navidad-1.0.0.dist-info/WHEEL
navidad-1.0.0.dist-info/entry_points.txt
navidad-1.0.0.dist-info/top_level.txt
navidad-1.0.0.dist-info/RECORD
