Metadata-Version: 2.4
Name: navidad
Version: 1.0.0
Summary: 🎄 Un árbol de navidad colorido en tu terminal - Feliz Navidad!
Author-email: Tu Nombre <tu@email.com>
License: MIT
Project-URL: Homepage, https://github.com/tu-usuario/navidad
Project-URL: Repository, https://github.com/tu-usuario/navidad.git
Keywords: navidad,christmas,arbol,tree,ascii,terminal,feliz navidad
Classifier: Development Status :: 5 - Production/Stable
Classifier: Environment :: Console
Classifier: Intended Audience :: Developers
Classifier: Intended Audience :: End Users/Desktop
Classifier: License :: OSI Approved :: MIT License
Classifier: Programming Language :: Python :: 3
Classifier: Programming Language :: Python :: 3.7
Classifier: Programming Language :: Python :: 3.8
Classifier: Programming Language :: Python :: 3.9
Classifier: Programming Language :: Python :: 3.10
Classifier: Programming Language :: Python :: 3.11
Classifier: Programming Language :: Python :: 3.12
Classifier: Operating System :: OS Independent
Classifier: Topic :: Games/Entertainment
Requires-Python: >=3.7
License-File: LICENSE
Dynamic: license-file
